{
  "2237746768": {
    "status": "Other",
    "ts": "2026-05-01T15:06:55.400Z"
  },
  "2239063977": {
    "status": "Closed",
    "ts": "2026-04-30T20:09:25.973Z"
  },
  "2240320159": {
    "status": "Closed",
    "ts": "2026-05-01T20:00:39.523Z"
  },
  "2240325772": {
    "status": "Closed",
    "ts": "2026-05-01T19:58:26.444Z"
  },
  "2243550288": {
    "status": "Closed",
    "ts": "2026-05-01T20:00:32.557Z"
  },
  "2245353778": {
    "status": "Other",
    "ts": "2026-05-01T22:52:42.716Z"
  },
  "2246959213": {
    "status": "Closed",
    "ts": "2026-05-01T20:00:35.582Z"
  },
  "2247844580": {
    "status": "Closed",
    "ts": "2026-05-01T22:54:00.971Z"
  },
  "2248391808": {
    "status": "Closed",
    "ts": "2026-05-01T20:00:45.866Z"
  },
  "2248916917": {
    "status": "Closed",
    "ts": "2026-05-01T22:55:17.454Z"
  },
  "2252495242": {
    "status": "Closed",
    "ts": "2026-05-01T20:00:48.361Z"
  },
  "2252603499": {
    "status": "Other",
    "ts": "2026-05-01T22:56:42.739Z"
  },
  "2254254462": {
    "status": "Closed",
    "ts": "2026-05-01T20:00:51.493Z"
  },
  "2255754314": {
    "status": "Closed",
    "ts": "2026-05-01T22:57:42.476Z"
  },
  "2263930746": {
    "status": "Closed",
    "ts": "2026-05-01T20:01:45.104Z"
  },
  "2268924414": {
    "status": "Other",
    "ts": "2026-05-01T20:49:59.204Z"
  },
  "2275803824": {
    "status": "Closed",
    "ts": "2026-05-01T21:20:27.329Z"
  },
  "2283076261": {
    "status": "Closed",
    "ts": "2026-05-01T21:22:54.624Z"
  },
  "2287982098": {
    "status": "Closed",
    "ts": "2026-05-01T21:41:00.765Z"
  },
  "2292825487": {
    "status": "Closed",
    "ts": "2026-05-01T21:43:26.717Z"
  },
  "2293134094": {
    "status": "Closed",
    "ts": "2026-05-01T21:43:24.009Z"
  },
  "1001290369922103": {
    "status": "Closed",
    "ts": "2026-05-01T16:09:19.116Z"
  },
  "1002256328452051": {
    "status": "Closed",
    "ts": "2026-05-01T20:00:42.088Z"
  },
  "1002265770372055": {
    "status": "Closed",
    "ts": "2026-05-01T20:51:18.459Z"
  },
  "1002269976482056": {
    "status": "Closed",
    "ts": "2026-05-01T21:20:40.969Z"
  }
}